fs_warehouser/__init__.py
fs_warehouser/fs_warehouser.py
fs_warehouser/fs_warehouser_.py
fs_warehouser-1.0.6.dist-info/LICENSE
fs_warehouser-1.0.6.dist-info/METADATA
fs_warehouser-1.0.6.dist-info/WHEEL
fs_warehouser-1.0.6.dist-info/top_level.txt
fs_warehouser-1.0.6.dist-info/zip-safe
fs_warehouser-1.0.6.dist-info/RECORD
