Metadata-Version: 2.1
Name: fs-warehouser
Version: 1.0.6
Summary: Filesystem based data warehousing framework
Home-page: https://github.com/JesseAldridge/fs_warehouser
Author: Jesse Aldridge
Author-email: JesseAldridge@gmail.com
License: MIT
Keywords: data-warehouse
Platform: UNKNOWN
License-File: LICENSE
